DataRefine/__init__.py
DataRefine/data_quality_assessment.py
DataRefine/handle_missing.py
DataRefine/handle_outliers.py
DataRefine/normalize.py
DataRefine/scripts/app.py
DataRefine/scripts/drlogo.jpeg
DataRefine/scripts/run_app.py
DataRefine-1.0.dist-info/LICENSE
DataRefine-1.0.dist-info/METADATA
DataRefine-1.0.dist-info/WHEEL
DataRefine-1.0.dist-info/entry_points.txt
DataRefine-1.0.dist-info/top_level.txt
DataRefine-1.0.dist-info/RECORD
