Metadata-Version: 2.1
Name: DataRefine
Version: 1.0
Summary: A no-code solution for performing data cleaning like misssing value imputation,outlier handling,normalisation,transformation and quality check with an intuitive interface for interactive DataFrame manipulation and easy CSV export.
Home-page: https://github.com/Shahanafarvin/DataRefine
Author: Shahana Farvin
Author-email: shahana50997@gmail.com
License: UNKNOWN
Project-URL: Documentation, https://github.com/Shahanafarvin/DataRefine/blob/main/README.md
Project-URL: Source, https://github.com/Shahanafarvin/DataRefine/tree/main/datarefine
Project-URL: Tracker, https://github.com/Shahanafarvin/DataRefine/issues
Keywords: data transformation,missing value imputation,outlier handling,normalisation,transformation,machine learning,data preprocessing,pandas,scikit-learn,feature engineering,data science,Python
Platform: UNKNOWN
Classifier: Development Status :: 5 - Production/Stable
Classifier: Intended Audience :: Developers
Classifier: License :: OSI Approved :: MIT License
Classifier: Programming Language :: Python :: 3.8
Classifier: Programming Language :: Python :: 3.9
Classifier: Programming Language :: Python :: 3.10
Classifier: Programming Language :: Python :: 3.11
Classifier: Programming Language :: Python :: 3.12
Classifier: Topic :: Software Development :: Libraries :: Python Modules
Requires-Python: >=3.8
License-File: LICENSE
Requires-Dist: numpy
Requires-Dist: pandas>=1.0.0
Requires-Dist: plotly
Requires-Dist: scikit-learn>=0.22.0
Requires-Dist: scipy
Requires-Dist: setuptools
Requires-Dist: streamlit
